Metadata-Version: 1.0
Name: distributions-GaussBino
Version: 0.1
Summary: Gaussian and Binomial distributions
Home-page: UNKNOWN
Author: Pongrak Keawsrinuan
Author-email: pongrak.k@hotmail.com
License: UNKNOWN
Platform: UNKNOWN
